{"6EbKa5sRBtPD6i6mG6wpIg==":"casella%20frente%2002-1260x845.png","5VFiHndQ+//XCDJwe9/hHQ==":"casella%20logo%20transparente%203-204x73.png","2mcdvQLrSV7U0HoswEA8og==":"casella%20adentro-1076x1076.jpg","6k8eJtfxpkYA9hG1ENMD1Q==":"mbr-1920x1281.jpg","BF3Nu8gtChzFOLvI1EET4w==":"casella%20imagen%2001-797x497.jpg","rPcMDYeWE/lwISbab2M50A==":"casella%20imagen%2001-797x497.jpg","JDUGvVxJGrslVOzhed6mNA==":"casella%20imagen%202-1153x719.jpg","/5MgH48ME4wV3s+NNfSk5w==":"casella%20imagen%205-1076x806.jpg","7RBFmtAskLkS6GK+wWQ5NQ==":"casella%20imagen%202-1153x719.jpeg","7CUifCBovuPVMpnXro721A==":"casella%20imagen%203-764x430.jpeg","y2XBPuRy0KWiGIi4Cb8wfg==":"casella%20imagen%203-764x430.jpeg","j/Kzhf4wP8HM6wuCB+fp2g==":"casella%20imagen%205-1076x806.jpeg","04JeKpL9tFcMcWqcyQK9pA==":"casella%20imagen%204-671x446.jpeg","IL7jTfE2fAjZiVU5XfF7zQ==":"mbr-1920x1116.jpg","inL5iLFvN1s/9Ua51FpZPA==":"casella_fotos-6-648x432.jpg","77b0iovKVoILexU8ihOL8A==":"casella_fotos-1-692x431.jpg","Rq+mn7JY5KsTujdkHupbNg==":"casella_fotos-2-691x431.jpg","zhOgu9sIvqUUO850cQTSVQ==":"casella_fotos-3-686x432.jpg","Iaduw2vKl9NvZqS/tBEtlg==":"casella_fotos-4-686x421.jpg","703jGkvtoXpxbZTG7S89UA==":"features2.jpg","HUfpc9SvDwBk7sbVG2SgiA==":"features3.jpg","oRykAiO0rUD++7AmPeEwUg==":"background1.jpg","Cesjxe6cW0NYFSAP4kiRig==":"features1.jpg","WeIcOp+qLfFEPxVAXUUAEA==":"features4.jpg","6YkOjahTk/cPHhB/paSY6g==":"casella_fotos-5-557x365.jpg","3rVkVBj+/lMjUSwmD94nvw==":"casella_fotos-6-557x371.jpg","l4dkD5IxQcHC7GNA0nQ6cA==":"casella_fotos-7-557x420.jpg","/1UQqURpqAHKqJM5zGFMtg==":"casella_fotos-8-557x418.jpg","zyz5TaDJMw41rHnVc2IGKQ==":"casella_fotos-9-432x431.jpg","G9FDHZJKIDivNcc0L0nNcw==":"casella_fotos-10-366x431.jpg","4s2MbNPTJFKmhu7vQsDPlg==":"casella_fotos-11-557x418.jpg","co7yZzeO8mXY74U8Dulu1g==":"casella_fotos-12-557x417.jpg","v/vkMppId5sFaOLpy4pV4A==":"casella_fotos-13-557x419.jpg","QiUWAGhIu4/4/HWs4IjXuw==":"casella_fotos-14-508x431.jpg","kkK3s5PqMHWhcxEp7FN01w==":"casella_fotos-15-557x285.jpg","hJIpaas5bz/AD9JAzgekoA==":"casella_fotos-16-323x430.jpg"}